{
  "date": "20260627",
  "venue": "hakodate",
  "place": "02",
  "as_of": "2026-06-26T(事前)",
  "odds_available": false,
  "races": [
    {
      "r": 7,
      "surface": "芝",
      "distance": 2000,
      "headcount": 11,
      "class": "3歳上1勝クラス",
      "race_type": "定量/別定",
      "race_name": "サラ系3歳上1勝クラス",
      "cond_rage": "弱",
      "cond_flags": [
        "中距離"
      ],
      "dango_tier": null,
      "dango_signals": [],
      "x_axis": {
        "anchor": [
          "ドウアドバンテージ",
          "マカナアネラ"
        ],
        "confidence": "割れて絞れない",
        "market_divergence": null,
        "field_legs": "逃0/先4/差3/追4",
        "concern": "主軸が連続2着で勝ち切れず、3歳の格上経験・昇級勢が複数横並びで対抗読みにくい"
      },
      "quadrant": "切り",
      "score": -1,
      "cut_reason": "逃げ不在（逃0＝ペースメーカー不在で展開が読めない）",
      "post_time": "13:10"
    },
    {
      "r": 10,
      "surface": "芝",
      "distance": 2000,
      "headcount": 11,
      "class": "2勝クラス特別",
      "race_type": "定量/別定",
      "race_name": "洞爺湖特別",
      "cond_rage": "弱",
      "cond_flags": [
        "中距離"
      ],
      "dango_tier": null,
      "dango_signals": [],
      "x_axis": {
        "anchor": [
          "バルティカ",
          "レイヤードレッド"
        ],
        "confidence": "割れて絞れない",
        "market_divergence": null,
        "field_legs": "逃0/先0/差4/追7",
        "concern": "能力団子＋追込偏重で展開頼み。前止まらず凡走リスクが全頭に均等"
      },
      "quadrant": "切り",
      "score": -1,
      "cut_reason": "逃げ不在（逃0＝ペースメーカー不在で展開が読めない）",
      "post_time": "14:45"
    },
    {
      "r": 11,
      "surface": "芝",
      "distance": 1200,
      "headcount": 14,
      "class": "青函S(OP)",
      "race_type": "定量/別定",
      "race_name": "青函ステークス",
      "cond_rage": "中",
      "cond_flags": [
        "函館開催",
        "芝短距離",
        "OP特別"
      ],
      "dango_tier": null,
      "dango_signals": [],
      "x_axis": {
        "anchor": [
          "ティニア",
          "ルージュラナキラ"
        ],
        "confidence": "割れて絞れない",
        "market_divergence": null,
        "field_legs": "逃0/先3/差6/追5",
        "concern": "逃げ不在で隊列読めず、近走OP特別で7-12着が横並び＝突出馬なし、展開引き当て勝負"
      },
      "quadrant": "切り",
      "score": -1,
      "cut_reason": "逃げ不在（逃0＝ペースメーカー不在で展開が読めない）",
      "post_time": "15:20"
    },
    {
      "r": 1,
      "surface": "芝",
      "distance": 1200,
      "headcount": 16,
      "class": "未勝利",
      "race_type": "—",
      "race_name": "サラ系3歳未勝利",
      "cond_rage": "強",
      "cond_flags": [
        "函館開催",
        "多頭数",
        "芝短距離"
      ],
      "dango_tier": null,
      "dango_signals": [],
      "x_axis": null,
      "quadrant": "見送り",
      "score": -3,
      "post_time": "09:50"
    },
    {
      "r": 2,
      "surface": "ダ",
      "distance": 1000,
      "headcount": 12,
      "class": "未勝利",
      "race_type": "—",
      "race_name": "サラ系3歳未勝利",
      "cond_rage": "弱",
      "cond_flags": [
        "函館開催"
      ],
      "dango_tier": null,
      "dango_signals": [],
      "x_axis": null,
      "quadrant": "見送り",
      "score": -3,
      "post_time": "10:20"
    },
    {
      "r": 3,
      "surface": "ダ",
      "distance": 1700,
      "headcount": 12,
      "class": "未勝利",
      "race_type": "—",
      "race_name": "サラ系3歳未勝利",
      "cond_rage": "弱",
      "cond_flags": [
        "函館開催"
      ],
      "dango_tier": null,
      "dango_signals": [],
      "x_axis": null,
      "quadrant": "見送り",
      "score": -3,
      "post_time": "10:50"
    },
    {
      "r": 4,
      "surface": "芝",
      "distance": 1800,
      "headcount": 16,
      "class": "未勝利",
      "race_type": "—",
      "race_name": "サラ系3歳未勝利",
      "cond_rage": "中",
      "cond_flags": [
        "函館開催",
        "多頭数"
      ],
      "dango_tier": null,
      "dango_signals": [],
      "x_axis": null,
      "quadrant": "見送り",
      "score": -3,
      "post_time": "11:20"
    },
    {
      "r": 5,
      "surface": "芝",
      "distance": 1200,
      "headcount": 8,
      "class": "新馬",
      "race_type": "—",
      "race_name": "サラ系2歳新馬",
      "cond_rage": "弱",
      "cond_flags": [
        "函館開催",
        "少頭数",
        "芝短距離"
      ],
      "dango_tier": null,
      "dango_signals": [],
      "x_axis": null,
      "quadrant": "見送り",
      "score": -3,
      "post_time": "12:10"
    },
    {
      "r": 6,
      "surface": "ダ",
      "distance": 1700,
      "headcount": 11,
      "class": "未勝利",
      "race_type": "—",
      "race_name": "サラ系3歳未勝利",
      "cond_rage": "弱",
      "cond_flags": [
        "函館開催"
      ],
      "dango_tier": null,
      "dango_signals": [],
      "x_axis": null,
      "quadrant": "見送り",
      "score": -3,
      "post_time": "12:40"
    },
    {
      "r": 8,
      "surface": "ダ",
      "distance": 1000,
      "headcount": 11,
      "class": "1勝クラス",
      "race_type": "—",
      "race_name": "サラ系3歳上1勝クラス",
      "cond_rage": "弱",
      "cond_flags": [
        "函館開催"
      ],
      "dango_tier": null,
      "dango_signals": [],
      "x_axis": null,
      "quadrant": "見送り",
      "score": -3,
      "post_time": "13:40"
    },
    {
      "r": 9,
      "surface": "芝",
      "distance": 1200,
      "headcount": 9,
      "class": "特別/OP",
      "race_type": "—",
      "race_name": "長万部特別",
      "cond_rage": "中",
      "cond_flags": [
        "函館開催",
        "芝短距離"
      ],
      "dango_tier": null,
      "dango_signals": [],
      "x_axis": null,
      "quadrant": "見送り",
      "score": -3,
      "post_time": "14:10"
    },
    {
      "r": 12,
      "surface": "ダ",
      "distance": 1700,
      "headcount": 10,
      "class": "1勝クラス",
      "race_type": "—",
      "race_name": "サラ系3歳上1勝クラス",
      "cond_rage": "弱",
      "cond_flags": [
        "函館開催"
      ],
      "dango_tier": null,
      "dango_signals": [],
      "x_axis": null,
      "quadrant": "見送り",
      "score": -3,
      "post_time": "16:05"
    }
  ]
}