{
  "schema_version": "1.0",
  "race_id": "20260712-hakodate-11",
  "race_name": "巴賞",
  "edition": "",
  "race_no": 11,
  "grade": "オープン",
  "date": "2026-07-12",
  "course": {
    "track": "函館",
    "surface": "芝",
    "distance": 1800,
    "direction": "右・小回り"
  },
  "conditions": "3歳以上オープン・別定",
  "field_size": 14,
  "model_version": "5.0",
  "used_observations": [
    "A",
    "B",
    "C",
    "D",
    "E",
    "G",
    "I",
    "K",
    "L"
  ],
  "header_notes": [
    "枠順・騎手・斤量は確定済み。馬場・馬体重・パドックは当日更新対象。",
    "観点並列はローカルCLIの互換性問題で停止。JRA公式seed、静的カタログ、決定論ツールで縮退合成。",
    "win_prob/place_prob は決定論エンジンの参考列。並びは印と行順を主に見る。",
    "観点欠落(F,H): 調教と当日気配は未反映。",
    "当日更新(7/12 13:55): 芝重・クッション値6.2（軟化継続）・当日芝は前残り連発＝前有利。β(先団消耗差し)を対抗→伏線、γ(⑧単騎スロー)を伏線→対抗に付け替え。⑧を注→△(4位)へ、β依存の②⑤を△→注へ。出走取消・騎手変更なし。"
  ],
  "pivot": "⑧が単騎で息を入れられるか、前走逃げた③と④⑨⑩⑬の前付けで先団が消耗するか。",
  "day_board": {
    "reference_races": [
      {
        "label": "函館2R",
        "when": "10:20",
        "course": "芝2000m",
        "match": "芝中距離",
        "watch": "内外の伸びと4角位置"
      },
      {
        "label": "函館5R",
        "when": "12:10",
        "course": "芝1800m",
        "match": "★同条件・新馬",
        "watch": "コーナーでの位置損と直線の伸び位置"
      },
      {
        "label": "函館9R 北海ハンデキャップ",
        "when": "14:10",
        "course": "芝1800m",
        "match": "★同条件・14頭",
        "watch": "先行負荷、4角位置、差しの届く範囲"
      }
    ],
    "reference_note": "9Rの同距離・同頭数を最重視し、2Rと5Rで芝中距離の伸び位置を補助確認。",
    "observation_blanks": "ペース層 / 内外バイアス / 決まり手 / 伸び位置",
    "going": [
      {
        "item": "馬場状態",
        "value": "雨・重（クッション値6.2＝金7.7→土7.0→日6.2と軟化継続）。当日芝2/4/5/6Rは逃げ先行の押し切りが続き前有利",
        "read": "内前が残る当日傾向を確認済み→α・γを上げβを下げた（反映済み）"
      },
      {
        "item": "馬体重",
        "value": "",
        "read": "休み明け⑨⑪⑫と、近走不振①⑦⑩⑬の増減を確認"
      }
    ],
    "paddock_watch": [
      {
        "mark": "◎",
        "gate_no": 4,
        "horse": "シルトホルン",
        "weight_note": "58kgでも張りと前進気勢を保てるか"
      },
      {
        "mark": "◯",
        "gate_no": 9,
        "horse": "レディネス",
        "weight_note": "休養明けの緩さと発汗"
      },
      {
        "mark": "▲",
        "gate_no": 3,
        "horse": "タシット",
        "weight_note": "7歳でも活気と踏み込みを維持するか"
      }
    ],
    "other_unknowns": [
      "当日芝の内外差",
      "③と⑧の先手争い",
      "⑨の休養明け仕上がり",
      "調教と直前気配は未確認"
    ]
  },
  "pace": {
    "verification_contract": "隊列・脚質有利不利・段階フローを着順とは別に固定し、レース後に独立採点する。",
    "pace_factors": [
      {
        "factor": "先行勢の数と質",
        "reads": "明確な逃げは⑧だが、前走逃げた③と④⑨⑩⑬も前受け可能。⑧が楽なら前残り、③が絡めば差し台頭。",
        "day_check": "③が⑧へ寄せるか、⑩⑬が外から出すか"
      },
      {
        "factor": "枠の効き",
        "reads": "③④は内から位置損を抑えやすい。⑭は外から差すため3角までの距離損が鍵。",
        "day_check": "内の伸びと⑭の初角位置"
      },
      {
        "factor": "コース形状",
        "reads": "函館芝1800は小回り短直線。後方一気より、3角から動ける好位・中団を優先。",
        "day_check": "5Rと9Rで4角位置がどこまで効くか"
      },
      {
        "factor": "例年傾向（過去開催）",
        "reads": "機械履歴は今回未取得。同距離・同頭数の当日9Rを優先する。",
        "day_check": "9Rの隊列と決まり手"
      },
      {
        "factor": "当日で動く点",
        "reads": "差しが連続すればβ、内前が残ればα・γへ寄せる。",
        "day_check": "2R、5R、9Rの伸び位置"
      }
    ],
    "leg_table": [
      {
        "gate": "1",
        "no": 1,
        "horse": "エラトー",
        "jockey": "北村 友一",
        "trainer": "上村 洋行",
        "leg_type": "差",
        "recent_pos": "6/3/5/3",
        "expected_pos": "中団"
      },
      {
        "gate": "2",
        "no": 2,
        "horse": "パレハ",
        "jockey": "佐々木 大輔",
        "trainer": "新谷 功一",
        "leg_type": "差",
        "recent_pos": "10/6/10/12",
        "expected_pos": "中団"
      },
      {
        "gate": "3",
        "no": 3,
        "horse": "タシット",
        "jockey": "横山 琉人",
        "trainer": "中川 公成",
        "leg_type": "差",
        "recent_pos": "1/5/4/5",
        "expected_pos": "中団"
      },
      {
        "gate": "3",
        "no": 4,
        "horse": "シルトホルン",
        "jockey": "丹内 祐次",
        "trainer": "新開 幸一",
        "leg_type": "先",
        "recent_pos": "3/3/10/5",
        "expected_pos": "先団"
      },
      {
        "gate": "4",
        "no": 5,
        "horse": "キョウエイブリッサ",
        "jockey": "浜中 俊",
        "trainer": "武市 康男",
        "leg_type": "差",
        "recent_pos": "17/7/8/11",
        "expected_pos": "中団"
      },
      {
        "gate": "4",
        "no": 6,
        "horse": "レディントン",
        "jockey": "小沢 大仁",
        "trainer": "杉山 晴紀",
        "leg_type": "先",
        "recent_pos": "2/4/8/8",
        "expected_pos": "先団"
      },
      {
        "gate": "5",
        "no": 7,
        "horse": "エエヤン",
        "jockey": "古川 吉洋",
        "trainer": "伊藤 大士",
        "leg_type": "追",
        "recent_pos": "15/16/13",
        "expected_pos": "後方"
      },
      {
        "gate": "5",
        "no": 8,
        "horse": "ストレイトトーカー",
        "jockey": "横山 武史",
        "trainer": "岩戸 孝樹",
        "leg_type": "逃",
        "recent_pos": "1/1/2/2",
        "expected_pos": "ハナ"
      },
      {
        "gate": "6",
        "no": 9,
        "horse": "レディネス",
        "jockey": "横山 和生",
        "trainer": "昆 貢",
        "leg_type": "先",
        "recent_pos": "3/4/8/12",
        "expected_pos": "先団"
      },
      {
        "gate": "6",
        "no": 10,
        "horse": "ヴーレヴー",
        "jockey": "吉田 隼人",
        "trainer": "武 幸四郎",
        "leg_type": "先",
        "recent_pos": "4/4/11/8",
        "expected_pos": "先団"
      },
      {
        "gate": "7",
        "no": 11,
        "horse": "パトリックハンサム",
        "jockey": "斎藤 新",
        "trainer": "柄崎 将寿",
        "leg_type": "追",
        "recent_pos": "6/3/11/11",
        "expected_pos": "後方"
      },
      {
        "gate": "7",
        "no": 12,
        "horse": "レディーヴァリュー",
        "jockey": "武 豊",
        "trainer": "小林 真也",
        "leg_type": "差",
        "recent_pos": "8/10/2/2",
        "expected_pos": "中団"
      },
      {
        "gate": "8",
        "no": 13,
        "horse": "ウインシュクラン",
        "jockey": "黛 弘人",
        "trainer": "和田 正一郎",
        "leg_type": "先",
        "recent_pos": "2/4/2/8",
        "expected_pos": "先団"
      },
      {
        "gate": "8",
        "no": 14,
        "horse": "リラボニート",
        "jockey": "鮫島 克駿",
        "trainer": "須貝 尚介",
        "leg_type": "差",
        "recent_pos": "12/5/5/2",
        "expected_pos": "中団"
      }
    ],
    "patterns": [
      {
        "id": "α",
        "name": "好位持続",
        "tier": "本線",
        "prob": 0.43,
        "trigger": "⑧が主導し、③④⑨が競らず好位で折り合う",
        "pace_level": 0.52,
        "contesters": [
          8,
          3,
          4,
          9
        ],
        "leg_advantage": {
          "逃げ": 1,
          "先行": 2,
          "差し": 0,
          "追込": -2
        },
        "formation_head": [
          8,
          3,
          4,
          9
        ],
        "formation_last_corner": [
          8,
          3,
          4,
          9,
          10,
          1
        ],
        "bias": "小回りの位置差を保ち、好位の地力上位が持続する。",
        "phase_flow": {
          "early": "⑧が先手を取り、③④⑨が直後で距離損を抑える。",
          "mid": "⑧が極端には緩めず、好位勢が追走力で隊列を維持する。",
          "late": "④⑨が早めに⑧へ並び、③が内で粘る。",
          "result": "④⑨が中心で③⑧が続き、中団の①⑭は届く範囲が限られる。"
        },
        "risers": [
          1,
          3,
          4,
          8,
          9,
          10
        ],
        "sinkers": [
          6,
          7,
          11,
          12,
          13
        ]
      },
      {
        "id": "β",
        "name": "先団消耗で差し浮上",
        "tier": "伏線",
        "prob": 0.35,
        "trigger": "③が⑧に譲らず、④⑨⑩⑬も前へ寄せる",
        "pace_level": 0.69,
        "contesters": [
          8,
          3,
          4,
          9,
          10,
          13
        ],
        "leg_advantage": {
          "逃げ": -2,
          "先行": -1,
          "差し": 2,
          "追込": 1
        },
        "formation_head": [
          8,
          3,
          13,
          4
        ],
        "formation_last_corner": [
          8,
          4,
          9,
          3,
          14,
          2,
          5
        ],
        "bias": "先団の余力が削られ、内中団と早め差しが浮上する。",
        "phase_flow": {
          "early": "⑧に③⑬が寄せ、④⑨⑩も位置確保に脚を使う。",
          "mid": "息が入り切らず、先団の追走負担が蓄積する。",
          "late": "⑭②⑤が外と内から進出し、④⑨は地力で抵抗する。",
          "result": "⑭②が浮上し、④⑨が残り目。⑤①も展開が向けば圏内へ入る。"
        },
        "risers": [
          1,
          2,
          4,
          5,
          9,
          11,
          12,
          14
        ],
        "sinkers": [
          3,
          8,
          10,
          13
        ]
      },
      {
        "id": "γ",
        "name": "⑧単騎スロー",
        "tier": "対抗",
        "prob": 0.22,
        "trigger": "③が控え、④⑨も番手で折り合って⑧が単騎",
        "pace_level": 0.36,
        "contesters": [
          8
        ],
        "leg_advantage": {
          "逃げ": 2,
          "先行": 2,
          "差し": -1,
          "追込": -2
        },
        "formation_head": [
          8,
          4,
          9,
          3
        ],
        "formation_last_corner": [
          8,
          4,
          9,
          3,
          10
        ],
        "bias": "直線入口の位置差が残り、前受け勢が優位。",
        "phase_flow": {
          "early": "⑧が競られず先手を取り、④⑨③が直後で折り合う。",
          "mid": "隊列が落ち着き、前受け勢が余力を温存する。",
          "late": "⑧が先に加速し、④⑨が直後から追う。",
          "result": "⑧④⑨が中心で③⑩が続き、後方勢は展開待ち。"
        },
        "risers": [
          3,
          4,
          6,
          8,
          9,
          10,
          13
        ],
        "sinkers": [
          2,
          5,
          7,
          11,
          12,
          14
        ]
      }
    ],
    "shape_note": "⑧の主導が基本形。③④⑨が直後、⑩⑬が外から前へ寄せ、①②⑤⑭は中団以降。",
    "formation_note": "本線は⑧→③④⑨→⑩⑬→①②⑤⑭。",
    "bias_note": "小回りの位置差を初期値とするが、先団が密集すれば差しへ反転。",
    "counter_conditions": "函館2R・5R・9Rで外差しが連続すればβを本線へ。内前が残り続ければγを対抗へ。",
    "transmission": "⑧と③の先手争いを最優先。競らなければ④⑨⑧、競れば⑭②を上げる。",
    "box_reverse": [
      {
        "pattern": "α",
        "tier": "本線",
        "center": [
          3,
          4,
          9
        ],
        "inside": [
          1,
          8,
          10
        ],
        "spot": [
          2,
          5,
          14
        ],
        "drop": [
          6,
          7,
          11,
          12,
          13
        ]
      },
      {
        "pattern": "β",
        "tier": "対抗",
        "center": [
          2,
          14
        ],
        "inside": [
          1,
          4,
          5,
          9,
          11,
          12
        ],
        "spot": [
          6,
          7
        ],
        "drop": [
          3,
          8,
          10,
          13
        ]
      },
      {
        "pattern": "γ",
        "tier": "伏線",
        "center": [
          4,
          8,
          9
        ],
        "inside": [
          3,
          6,
          10,
          13
        ],
        "spot": [
          1
        ],
        "drop": [
          2,
          5,
          7,
          11,
          12,
          14
        ]
      }
    ]
  },
  "rank_verification_contract": "展開予想を先に固定し、本線の段階フローに各馬を通して印と行順を決定。率は並びを変更しない。",
  "rank": [
    {
      "no": 4,
      "gate": "3",
      "horse": "シルトホルン",
      "jockey": "丹内 祐次",
      "trainer": "新開 幸一",
      "jockey_change": "乗替",
      "intent": "↑",
      "mark": "◎",
      "rank_order": 1,
      "win_prob": 0.1839,
      "place_prob": 0.4848,
      "leg_type": "先",
      "pattern_fit": {
        "α": "◎",
        "β": "○",
        "γ": "◎"
      },
      "pace_sensitivity": "α・γで中心、βでも地力で残る。三展開で最も崩れにくい。",
      "pros": [
        {
          "tag": "B",
          "note": "福島民報杯3着、小倉大賞典5着、エプソムC7着と強い相手に安定。"
        },
        {
          "tag": "D",
          "note": "4番の内枠から前受けでき、小回りの位置損を抑えやすい。"
        },
        {
          "tag": "K",
          "note": "丹内騎手は福島民報杯3着時にも騎乗。"
        }
      ],
      "cons": [
        {
          "tag": "A",
          "note": "58kgで最後のひと押しに幅。"
        }
      ]
    },
    {
      "no": 9,
      "gate": "6",
      "horse": "レディネス",
      "jockey": "横山 和生",
      "trainer": "昆 貢",
      "jockey_change": "乗替",
      "intent": "→",
      "mark": "◯",
      "rank_order": 2,
      "win_prob": 0.1689,
      "place_prob": 0.4613,
      "leg_type": "先",
      "pattern_fit": {
        "α": "◎",
        "β": "○",
        "γ": "◎"
      },
      "pace_sensitivity": "α・γで中心、βでも好位から抵抗。休み明けだけが大きな死角。",
      "pros": [
        {
          "tag": "A",
          "note": "元町Sを1分44秒7、上がり33秒1で勝利。"
        },
        {
          "tag": "B",
          "note": "白富士S4着でオープン適応を示した。"
        },
        {
          "tag": "D",
          "note": "好位から3角で動ける脚質が函館に合う。"
        }
      ],
      "cons": [
        {
          "tag": "G",
          "note": "前走から162日の休み明け。仕上がり次第では印を下げる。"
        }
      ]
    },
    {
      "no": 3,
      "gate": "3",
      "horse": "タシット",
      "jockey": "横山 琉人",
      "trainer": "中川 公成",
      "jockey_change": "乗替",
      "intent": "↑",
      "mark": "▲",
      "rank_order": 3,
      "win_prob": 0.0871,
      "place_prob": 0.2647,
      "leg_type": "差",
      "pattern_fit": {
        "α": "◎",
        "γ": "○"
      },
      "pace_sensitivity": "αでは内好位で粘り、γでも圏内。βの先手争いでは消耗する。",
      "pros": [
        {
          "tag": "B",
          "note": "前走は東京1800で逃げて2着。近況が上向き。"
        },
        {
          "tag": "D",
          "note": "3番から前受けでき、内で余力を残しやすい。"
        },
        {
          "tag": "G",
          "note": "中4週で前走の状態を維持しやすい。"
        }
      ],
      "cons": [
        {
          "tag": "I",
          "note": "7歳で上積みは限定的。⑧と競るβでは消耗する。"
        }
      ]
    },
    {
      "no": 8,
      "gate": "5",
      "horse": "ストレイトトーカー",
      "jockey": "横山 武史",
      "trainer": "岩戸 孝樹",
      "jockey_change": "乗替",
      "intent": "→",
      "mark": "△",
      "rank_order": 4,
      "win_prob": 0.1036,
      "place_prob": 0.3164,
      "leg_type": "逃",
      "pattern_fit": {
        "α": "○",
        "γ": "◎"
      },
      "pace_sensitivity": "γ昇格の当日馬場で逃げ残り筆頭格。αでも残り目、βのみ被害馬。",
      "pros": [
        {
          "tag": "E",
          "note": "唯一の明確な逃げ脚質で展開の主導権を握る。"
        },
        {
          "tag": "K",
          "note": "横山武史騎手との組み合わせで逃げ切り歴。"
        }
      ],
      "cons": [
        {
          "tag": "B",
          "note": "前走エプソムCは逃げて16着。③らに絡まれるβでは余力を失う。"
        }
      ]
    },
    {
      "no": 14,
      "gate": "8",
      "horse": "リラボニート",
      "jockey": "鮫島 克駿",
      "trainer": "須貝 尚介",
      "jockey_change": "乗替",
      "intent": "↑",
      "mark": "△",
      "rank_order": 5,
      "win_prob": 0.0937,
      "place_prob": 0.2812,
      "leg_type": "差",
      "pattern_fit": {
        "β": "◎"
      },
      "pace_sensitivity": "βの差し中心。α・γでは外枠と位置差が重い。",
      "pros": [
        {
          "tag": "A",
          "note": "上がり33秒3の決め手があり、βなら終盤に浮上。"
        },
        {
          "tag": "B",
          "note": "洛陽S3着、ターコイズS2着の実績。"
        }
      ],
      "cons": [
        {
          "tag": "D",
          "note": "14番から差すため3角までの距離損が大きい。"
        },
        {
          "tag": "B",
          "note": "近走は1600以下が中心で1800への対応に幅。"
        }
      ]
    },
    {
      "no": 2,
      "gate": "2",
      "horse": "パレハ",
      "jockey": "佐々木 大輔",
      "trainer": "新谷 功一",
      "jockey_change": "乗替",
      "intent": "→",
      "mark": "注",
      "rank_order": 6,
      "win_prob": 0.0651,
      "place_prob": 0.2053,
      "leg_type": "差",
      "pattern_fit": {
        "β": "◎"
      },
      "pace_sensitivity": "βで内から差し浮上。前残りでは仕掛け遅れが課題。",
      "pros": [
        {
          "tag": "B",
          "note": "福島記念3着があり、消耗戦で内から差す形に対応。"
        },
        {
          "tag": "D",
          "note": "2番で距離損を抑えられる。"
        }
      ],
      "cons": [
        {
          "tag": "E",
          "note": "テンが遅く、α・γでは位置差を詰めにくい。"
        }
      ]
    },
    {
      "no": 5,
      "gate": "4",
      "horse": "キョウエイブリッサ",
      "jockey": "浜中 俊",
      "trainer": "武市 康男",
      "jockey_change": "乗替",
      "intent": "→",
      "mark": "注",
      "rank_order": 7,
      "win_prob": 0.0718,
      "place_prob": 0.2235,
      "leg_type": "差",
      "pattern_fit": {
        "β": "○"
      },
      "pace_sensitivity": "βで決め手が生きる。平均以下では後方位置が重い。",
      "pros": [
        {
          "tag": "A",
          "note": "[A]マイラーズC 10着・1:32.1・上がり32.8を加点材料とする。"
        },
        {
          "tag": "B",
          "note": "[B]マイラーズC 10着・1:32.1・上がり32.8を加点材料とする。"
        },
        {
          "tag": "C",
          "note": "[C]父グレーターロンドン、母父ルーラーシップの構成を芝1800の持続戦材料として評価。"
        },
        {
          "tag": "K",
          "note": "[K]前走田山 旺佑騎手から浜中 俊騎手へ交代。"
        }
      ],
      "cons": []
    },
    {
      "no": 1,
      "gate": "1",
      "horse": "エラトー",
      "jockey": "北村 友一",
      "trainer": "上村 洋行",
      "jockey_change": "乗替",
      "intent": "→",
      "mark": "注",
      "rank_order": 8,
      "win_prob": 0.0473,
      "place_prob": 0.1542,
      "leg_type": "差",
      "pattern_fit": {
        "α": "○",
        "β": "○"
      },
      "pace_sensitivity": "α・βで内を立ち回れば圏内。近2走の下降基調が課題。",
      "pros": [
        {
          "tag": "C",
          "note": "[C]父Saxon Warrior、母父Siyouniの構成を芝1800の持続戦材料として評価。"
        },
        {
          "tag": "D",
          "note": "[D]福島牝馬S 13着・1:46.9・上がり35.4を加点材料とする。"
        }
      ],
      "cons": [
        {
          "tag": "B",
          "note": "[B]福島牝馬S 13着・1:46.9・上がり35.4から割引。"
        },
        {
          "tag": "I",
          "note": "[I]直近2走連続大敗を一次リスクとして扱う。"
        }
      ]
    },
    {
      "no": 10,
      "gate": "6",
      "horse": "ヴーレヴー",
      "jockey": "吉田 隼人",
      "trainer": "武 幸四郎",
      "jockey_change": "乗替",
      "intent": "→",
      "mark": "注",
      "rank_order": 9,
      "win_prob": 0.0468,
      "place_prob": 0.1592,
      "leg_type": "先",
      "pattern_fit": {
        "α": "○",
        "γ": "○"
      },
      "pace_sensitivity": "α・γで好位残り。βでは芝戻り初戦と消耗が重なる。",
      "pros": [
        {
          "tag": "C",
          "note": "[C]父サトノクラウン、母父マンハッタンカフェの構成を芝1800の持続戦材料として評価。"
        }
      ],
      "cons": [
        {
          "tag": "B",
          "note": "[B]ポラリスS 16着・1:25.4・上がり39.5から割引。"
        },
        {
          "tag": "I",
          "note": "[I]直近2走連続大敗を一次リスクとして扱う。"
        }
      ]
    },
    {
      "no": 12,
      "gate": "7",
      "horse": "レディーヴァリュー",
      "jockey": "武 豊",
      "trainer": "小林 真也",
      "jockey_change": "乗替",
      "intent": "→",
      "mark": "×",
      "rank_order": 10,
      "win_prob": 0.0321,
      "place_prob": 0.1073,
      "leg_type": "差",
      "pattern_fit": {
        "β": "○"
      },
      "pace_sensitivity": "βで差し目はあるが、休み明けと近2走大敗で上位までは割引。",
      "pros": [
        {
          "tag": "C",
          "note": "[C]父ジャスタウェイ、母父Coronado's Questの構成を芝1800の持続戦材料として評価。"
        },
        {
          "tag": "K",
          "note": "[K]前走団野 大成騎手から武 豊騎手へ交代。"
        }
      ],
      "cons": [
        {
          "tag": "A",
          "note": "[A]中山牝馬S 16着・1:48.9・上がり36.8から割引。"
        },
        {
          "tag": "B",
          "note": "[B]中山牝馬S 16着・1:48.9・上がり36.8から割引。"
        },
        {
          "tag": "D",
          "note": "[D]12番の外寄り・後方想定で3角までの位置差が課題。"
        },
        {
          "tag": "G",
          "note": "[G]中山牝馬S 16着・1:48.9・上がり36.8から割引。"
        }
      ]
    },
    {
      "no": 6,
      "gate": "4",
      "horse": "レディントン",
      "jockey": "小沢 大仁",
      "trainer": "杉山 晴紀",
      "jockey_change": "乗替",
      "intent": "→",
      "mark": "×",
      "rank_order": 11,
      "win_prob": 0.0308,
      "place_prob": 0.1067,
      "leg_type": "先",
      "pattern_fit": {
        "γ": "○"
      },
      "pace_sensitivity": "γで前残りの余地はあるが、近走ダート中心で芝1800の裏付けが薄い。",
      "pros": [
        {
          "tag": "G",
          "note": "[G]アハルテケS 9着・1:36.5・上がり37.8を加点材料とする。"
        }
      ],
      "cons": [
        {
          "tag": "A",
          "note": "[A]アハルテケS 9着・1:36.5・上がり37.8から割引。"
        },
        {
          "tag": "B",
          "note": "[B]アハルテケS 9着・1:36.5・上がり37.8から割引。"
        },
        {
          "tag": "L",
          "note": "[L]外部の過去開催照合なし。"
        },
        {
          "tag": "D",
          "note": "γで位置は向いても、近走ダート中心で芝1800の裏付けが薄い。"
        }
      ]
    },
    {
      "no": 11,
      "gate": "7",
      "horse": "パトリックハンサム",
      "jockey": "斎藤 新",
      "trainer": "柄崎 将寿",
      "jockey_change": "乗替",
      "intent": "↓",
      "mark": "×",
      "rank_order": 12,
      "win_prob": 0.0204,
      "place_prob": 0.0689,
      "leg_type": "追",
      "pattern_fit": {
        "β": "○"
      },
      "pace_sensitivity": "βで前崩れなら進出余地も、長期休養明けで反応の保証がない。",
      "pros": [
        {
          "tag": "L",
          "note": "[L]前年函館芝1800の出走歴がある。"
        }
      ],
      "cons": [
        {
          "tag": "A",
          "note": "[A]WASJ2 1着・2:02.1・上がり36.5から割引。"
        },
        {
          "tag": "D",
          "note": "[D]11番の外寄り・後方想定で3角までの位置差が課題。"
        },
        {
          "tag": "G",
          "note": "[G]前走から約323日の長期休養明け。"
        },
        {
          "tag": "I",
          "note": "[I]7歳かつ長期休養明けを一次リスクとして扱う。"
        },
        {
          "tag": "B",
          "note": "βで展開が向いても約323日ぶりでは終盤の反応を保証できない。"
        }
      ]
    },
    {
      "no": 7,
      "gate": "5",
      "horse": "エエヤン",
      "jockey": "古川 吉洋",
      "trainer": "伊藤 大士",
      "jockey_change": "乗替",
      "intent": "↓",
      "mark": "×",
      "rank_order": 13,
      "win_prob": 0.019,
      "place_prob": 0.0643,
      "leg_type": "追",
      "pattern_fit": {},
      "pace_sensitivity": "βでも近走下降と59kgを覆す材料が薄い。",
      "pros": [],
      "cons": [
        {
          "tag": "A",
          "note": "[A]ダービーCT 12着・1:34.7・上がり35.6から割引。"
        },
        {
          "tag": "B",
          "note": "[B]ダービーCT 12着・1:34.7・上がり35.6から割引。"
        },
        {
          "tag": "D",
          "note": "[D]ダービーCT 12着・1:34.7・上がり35.6から割引。"
        },
        {
          "tag": "I",
          "note": "[I]直近2走連続大敗と59kgを一次リスクとして扱う。"
        }
      ]
    },
    {
      "no": 13,
      "gate": "8",
      "horse": "ウインシュクラン",
      "jockey": "黛 弘人",
      "trainer": "和田 正一郎",
      "jockey_change": "乗替",
      "intent": "↓",
      "mark": "×",
      "rank_order": 14,
      "win_prob": 0.0295,
      "place_prob": 0.1022,
      "leg_type": "先",
      "pattern_fit": {
        "γ": "○"
      },
      "pace_sensitivity": "γの先行残り候補にはなるが、8歳・平地近況不振・seed走破値異常で最下層。",
      "pros": [],
      "cons": [
        {
          "tag": "A",
          "note": "[A]前走の走破値はseed解析異常を含み、平地近況の信頼性が低い。"
        },
        {
          "tag": "B",
          "note": "[B]福島民報杯 15着・2:40.2から割引。"
        },
        {
          "tag": "D",
          "note": "[D]福島民報杯 15着・2:40.2から割引。"
        },
        {
          "tag": "I",
          "note": "[I]8歳かつ前走大敗を一次リスクとして扱う。"
        },
        {
          "tag": "B",
          "note": "γで前が残っても、平地近況の裏付けが乏しい。"
        }
      ]
    }
  ],
  "data_confidence": [
    {
      "item": "核データ",
      "level": "高",
      "note": "JRA公式出馬表seed。"
    },
    {
      "item": "展開・着順",
      "level": "低",
      "note": "外部調査なしの縮退合成。"
    }
  ],
  "reinforcement_requests": [
    "当日9R後の芝1800の決まり方",
    "⑨の馬体重とパドック気配",
    "③と⑧の先手意識"
  ]
}